{
  "$schema": "../../../../schema/account.schema.json",
  "address": "0xdc955ba9ab90b018ec234267ddd1f68ebd6fc6c8",
  "displayName": "Protocol of Protocol of Protocol of Protocol of Protocol of Protocol of Protocol of Protocol of Protocol of Protocol of Protocol of Protocol of Protocol of Protocol of Protocol of Protocol of Protocol of Protocol of Protocol of Protocol of Protocol of Protocol of Protocol of Protocol of Protocol of Protocol of Protocol of Protocol of Protocol of Protocol of Protocol of Protocol",
  "type": "TOKEN",
  "token": {
    "name": "Protocol of Protocol of Protocol of Protocol of Protocol of Protocol of Protocol of Protocol of Protocol of Protocol of Protocol of Protocol of Protocol of Protocol of Protocol of Protocol of Protocol of Protocol of Protocol of Protocol of Protocol of Protocol of Protocol of Protocol of Protocol of Protocol of Protocol of Protocol of Protocol of Protocol of Protocol of Protocol",
    "symbol": "PoPoPoPoPoPoPoPoPoPoPoPoPoPoPoPoPoPoPoPoPoPoP",
    "decimals": 9,
    "type": "ERC20"
  }
}