{
  "$schema": "../../../../schema/account.schema.json",
  "address": "0xb02f0f968a5e6cbd1590a4ca1c379b45af906f46",
  "displayName": "FOMO FOMO FOMO FOMO FOMO FOMO FOMO FOMO FOMO FOMO FOMO FOMO FOMO FOMO FOMO FOMO FOMO FOMO FOMO FOMO FOMO FOMO FOMO FOMO FOMO FOMO FOMO FOMO FOMO FOMO FOMO FOMO FOMO FOMO FOMO FOMO",
  "type": "TOKEN",
  "token": {
    "name": "FOMO FOMO FOMO FOMO FOMO FOMO FOMO FOMO FOMO FOMO FOMO FOMO FOMO FOMO FOMO FOMO FOMO FOMO FOMO FOMO FOMO FOMO FOMO FOMO FOMO FOMO FOMO FOMO FOMO FOMO FOMO FOMO FOMO FOMO FOMO FOMO",
    "symbol": "FOMO",
    "decimals": 9,
    "type": "ERC20"
  }
}